odooer/__init__.py
odooer/create_module.py
odooer-1.0.3.dist-info/METADATA
odooer-1.0.3.dist-info/WHEEL
odooer-1.0.3.dist-info/entry_points.txt
odooer-1.0.3.dist-info/top_level.txt
odooer-1.0.3.dist-info/RECORD
