Metadata-Version: 2.1
Name: odooer
Version: 1.0.3
Summary: A CLI tool for creating Odoo module boilerplate
Author: Muhammad Osama
Author-email: ocama_aslam@outlook.com
License: UNKNOWN
Keywords: Odoo CLI
Platform: UNKNOWN
